{
  "title": "十大 赌场 玩家 追踪 行为: 游戏 活动 监控 and 模式 分析 对比2026",
  "description": "Detailed 分析 of 赌场 玩家 追踪 行为 covering 游戏 活动 监控, 模式 分析, 行为 追踪, and 玩家 活动 intellig...。立即了解完整评测，找到最适合你的方案！",
  "content": "<h1>赌场 玩家 追踪 行为: 游戏 活动 监控 and 模式 分析</h1><h2>赌场 玩家 追踪 行为 Over视图</h2><p>赌场 玩家 追踪 行为 系统s re当前 专门的 平台s 监控 游戏 活动, analyzing 行为 模式s, and 追踪 玩家 行为 支持ing 全面的 赌场 行为 追踪. These 系统s monitor 游戏 活动, analyze 行为 模式s, and track 玩家 行为 ensuring 全面的 赌场 玩家 行为 追踪 能力.</p><h2>Leading 行为 追踪 解决方案s</h2><h3>Bally 行为 追踪 平台</h3><p>Bally 行为 追踪 平台 delivers 全面的 追踪 功能 集成 with Bally's 赌场 系统s, 优惠ing 游戏 活动 监控, 模式 分析, and 行为 追踪. Bally 行为 provides 全面的 赌场 活动 监控.</p><h3>IGT 行为 分析 系统</h3><p>IGT 行为 分析 系统 delivers 追踪 功能 集成 with IGT's 赌场 平台, 优惠ing 游戏 活动 监控, 模式 分析, and 行为 追踪. IGT 行为 provides 全面的 赌场 玩家 行为 能力.</p><h3>赌场 活动 监控 平台s</h3><p>赌场 活动 监控 平台s provide 全面的 行为 追踪, 优惠ing 游戏 活动 监控, 模式 分析, and 行为 追踪. 监控 平台s enable complete 赌场 玩家 行为 追踪.</p><h2>行为 追踪 平台 Comparison</h2><table><thead><tr><th>追踪 能力</th><th>Bally 行为</th><th>IGT 分析</th><th>监控 平台</th><th>追踪 Pro</th></tr></thead><tbody><tr><td>游戏 活动 监控</td><td>优秀的 活动 监控</td><td>全面的 监控 能力</td><td>标准 监控 功能s</td><td>先进的 活动 监控</td></tr><tr><td>模式 分析</td><td>优秀的 模式 分析</td><td>全面的 分析 能力</td><td>标准 分析 功能s</td><td>先进的 模式 分析</td></tr><tr><td>行为 追踪</td><td>优秀的 行为 追踪</td><td>全面的 追踪 能力</td><td>标准 追踪 功能s</td><td>先进的 行为 追踪</td></tr><tr><td>活动 智能</td><td>优秀的 活动 智能</td><td>全面的 智能 能力</td><td>标准 智能 功能s</td><td>先进的 活动 智能</td></tr></tbody></table><h2>核心 行为 追踪 功能</h2><p>赌场 玩家 行为 追踪 系统s deliver 游戏 活动 监控, 模式 分析, 行为 追踪, and 活动 智能. 理解 these capabilities enables 赌场 operators to implement effective 追踪 系统s 支持ing 玩家 行为 分析.</p><p>游戏 活动 监控 功能 monitors 赌场 游戏 活动, tracks 玩家 行为, and observes 游戏 模式s ensuring 全面的 游戏 活动 监控 能力. 监控 系统s ensure accurate 监控, proper 追踪, and 全面的 赌场 玩家 行为 observation.</p><p>模式 分析 功能 analyzes 赌场 行为 模式s, identifies 游戏 趋势s, and detects 玩家 模式s ensuring 全面的 模式 分析 能力. 分析 系统s ensure accurate 分析, proper 识别, and 全面的 赌场 玩家 行为 趋势 理解.</p><p>行为 追踪 功能 tracks 赌场 玩家 行为, monitors 游戏 活动, and observes 行为 模式s ensuring 全面的 行为 追踪 能力. 追踪 系统s ensure accurate 追踪, proper 监控, and 全面的 赌场 玩家 行为 模式 observation.</p><h2>游戏 活动 监控 系统s</h2><p>游戏 活动 监控 功能 monitors 赌场 游戏 活动, tracks 玩家 行为, and observes 游戏 模式s ensuring 全面的 游戏 活动 监控 能力. 监控 架构 addresses 活动 监控, 行为 追踪, and 模式 observation.</p><p>活动 监控 monitors 赌场 游戏 活动, tracks 玩家 行为, and observes 游戏 模式s ensuring 全面的 活动 监控 能力. 监控 系统s ensure accurate 监控, proper 追踪, and 全面的 赌场 玩家 行为 observation.</p><p>行为 追踪 tracks 赌场 玩家 行为, monitors 游戏 活动, and observes 行为 模式s ensuring 全面的 行为 追踪 能力. 追踪 系统s ensure accurate 追踪, proper 监控, and 全面的 赌场 玩家 行为 模式 observation.</p><p>模式 observation observes 赌场 游戏 模式s, monitors 玩家 行为, and tracks 模式 演变 ensuring 全面的 模式 observation 能力. Observation 系统s ensure accurate observation, proper 监控, and 全面的 赌场 游戏 模式 追踪.</p><h2>行为 模式 分析</h2><p>模式 分析 功能 analyzes 赌场 行为 模式s, identifies 游戏 趋势s, and detects 玩家 模式s ensuring 全面的 模式 分析 能力. 模式 架构 addresses 模式 分析, 趋势 识别, and 模式 检测.</p><p>模式 分析 analyzes 赌场 行为 模式s, identifies 游戏 趋势s, and detects 玩家 模式s ensuring 全面的 模式 分析 能力. 分析 系统s ensure accurate 分析, proper 识别, and 全面的 赌场 玩家 行为 趋势 理解.</p><p>趋势 识别 identifies 赌场 游戏 趋势s, analyzes 行为 模式s, and detects 玩家 趋势s ensuring 全面的 趋势 识别 能力. 识别 系统s ensure accurate 识别, proper 分析, and 全面的 赌场 玩家 行为 趋势 理解.</p><p>模式 检测 detects 赌场 玩家 模式s, identifies 行为 characteristics, and analyzes 模式 功能s ensuring 全面的 模式 检测 能力. 检测 系统s ensure accurate 检测, proper 识别, and 全面的 赌场 玩家 行为 模式 理解.</p><h2>行为 追踪 操作</h2><p>行为 追踪 功能 tracks 赌场 玩家 行为, monitors 游戏 活动, and observes 行为 模式s ensuring 全面的 行为 追踪 能力. 追踪 架构 addresses 行为 追踪, 活动 监控, and 模式 observation.</p><p>行为 追踪 tracks 赌场 玩家 行为, monitors 游戏 活动, and observes 行为 模式s ensuring 全面的 行为 追踪 能力. 追踪 系统s ensure accurate 追踪, proper 监控, and 全面的 赌场 玩家 行为 模式 observation.</p><p>活动 监控 monitors 赌场 游戏 活动, tracks 玩家 行为, and observes 活动 模式s ensuring 全面的 活动 监控 能力. 监控 系统s ensure accurate 监控, proper 追踪, and 全面的 赌场 玩家 活动 observation.</p><p>模式 observation observes 赌场 行为 模式s, monitors 玩家 活动, and tracks 模式 演变 ensuring 全面的 模式 observation 能力. Observation 系统s ensure accurate observation, proper 监控, and 全面的 赌场 玩家 行为 模式 追踪.</p><h2>实施 and 行为 追踪 设置</h2><p>行为 追踪 实施 requires 全面的 监控 preparation, 系统 配置, and 运营 设置 ensuring effective 行为 追踪 操作. 实施 activities address 监控 preparation, 系统 设置, and 运营 preparation.</p><p>监控 preparation establishes 追踪 foundations, creates 活动 监控 protocols, and ensures 追踪 readiness enabling reliable 追踪 流程ing. Preparation activities ensure proper foundations, accurate protocols, and 全面的 赌场 玩家 行为 追踪 readiness.</p><p>系统 配置 establishes 追踪 系统 设置, defines 监控 参数, and configures 分析 选项 matching 赌场 追踪 要求. 配置 activities ensure proper 设置, accurate 参数, and 全面的 行为 追踪 系统 设置.</p><p>运营 preparation ensures 追踪 操作 readiness, coordinates 监控 preparation, and prepares 分析 操作 ensuring 全面的 追踪 操作 readiness. Preparation activities ensure proper readiness, accurate preparation, and 全面的 赌场 玩家 行为 追踪 操作 preparation.</p><h2>未来 趋势s in 行为 追踪</h2><p>赌场 玩家 行为 追踪 系统s will advance toward AI-powered 模式 识别, 实时 行为 分析, and 预测 活动 模型ing. Deep 学习 algorithms will analyze complex 游戏 行为 模式s, enabling 复杂的 玩家 追踪 that captures nuanced 活动 characteristics.</p><p>集成 capabilities will expand to include 统一 行为 追踪 across 赌场 floors, 在线 游戏 平台s, and 移动 应用s. Real-time 行为 仪表板s will enable live 模式 监控, allowing operators to respond immediately to 玩家 行为 变更s and 新兴 游戏 趋势s.</p><p>先进的 privacy-preserving technologies will enable 行为 追踪 while protecting 玩家 数据 through anonymized 分析 and encrypted 行为 记录s. Blockchain-based 追踪 验证 may r演变ize 玩家 行为 文档 through immutable 活动 历史 and transparent 模式 记录s.</p>",
  "seo_keywords": [
    "赌场 玩家 追踪",
    "行为 分析 赌场",
    "游戏 活动 监控",
    "模式 分析 系统",
    "行为 追踪 平台",
    "玩家 活动 智能",
    "行为 模式 分析"
  ],
  "slug": "casino-player-tracking-behavioral-guide",
  "published_at": "2026-05-01",
  "author": "Behavioral Tracking Expert",
  "language": "zh-CN",
  "canonical_link": "https://www.housecar.life/posts/casino-player-tracking-behavioral-guide",
  "alternate_links": {
    "en-US": "https://www.housecar.life/posts/casino-player-tracking-behavioral-guide",
    "zh-CN": "https://www.housecar.life/zh/posts/casino-player-tracking-behavioral-guide"
  },
  "category": "casino-gaming-entertainment-tools"
}