{
  "title": "Agricultural IoT Platforms: Smart Farming Technology Guide - 2026 Review",
  "description": "Comprehensive review of agricultural IoT platforms in 2026. Compare sensor networks, monitoring systems, and connected farming technology solutions. Discov",
  "content": "<h1>Agricultural IoT Platforms: Smart Farming Technology Guide</h1><p>Internet of Things (IoT) technology has transformed agriculture into a data-driven industry. Agricultural IoT platforms connect sensors, equipment, and systems into unified monitoring and control networks. These platforms enable precision farming, automated operations, and real-time decision-making based on comprehensive field data.</p><h2>Understanding Agricultural IoT</h2><p>Agricultural IoT involves deploying sensors throughout farming operations—fields, equipment, storage facilities, and livestock areas. These sensors collect data on soil conditions, weather, crop health, equipment performance, and environmental factors. IoT platforms aggregate this data, analyze it, and enable automated or informed responses.</p><h2>Top Agricultural IoT Platforms Reviewed</h2><h3>1. John Deere Operations Center</h3><p>John Deere Operations Center provides comprehensive IoT integration for equipment-heavy operations. The platform connects tractors, implements, and field sensors into unified management. Its strength lies in deep integration with John Deere equipment ecosystem.</p><p><strong>Key Features:</strong></p><ul><li>Equipment telematics integration</li><li>Field sensor connectivity</li><li>Automated guidance systems</li><li>Real-time performance monitoring</li><li>Data analysis and reporting</li></ul><p><strong>Pricing:</strong> John Deere Operations Center is included with equipment purchases. Subscription features for non-JD equipment start at $50 monthly.</p><h3>2. FarmBeats by Microsoft</h3><p>FarmBeats leverages Microsoft's Azure IoT platform for agricultural applications. The system provides flexible sensor integration and data analysis. Its strength lies in Azure ecosystem integration and AI-powered analytics.</p><p><strong>Key Features:</strong></p><ul><li>Flexible sensor integration</li><li>Azure cloud analytics</li><li>AI-powered insights</li><li>Edge computing capabilities</li><li>Integration with farm management software</li></ul><p><strong>Pricing:</strong> FarmBeats pricing depends on Azure usage. Sensor packages start at $500, with cloud costs varying by data volume.</p><h3>3. Farmio</h3><p>Farmio offers purpose-built IoT for agriculture with comprehensive sensor packages. The platform provides soil, weather, and crop monitoring with automated alerts. Its strength lies in agricultural-specific sensors and easy deployment.</p><p><strong>Key Features:</strong></p><ul><li>Soil moisture and temperature sensors</li><li>Weather station integration</li><li>Crop health monitoring</li><li>Automated alerts and notifications</li><li>Mobile dashboard</li></ul><p><strong>Pricing:</strong> Farmio sensor packages start at $1,000 for basic monitoring. Platform subscription is $29 monthly for data management.</p><h2>Platform Comparison Table</h2><table><thead><tr><th>Platform</th><th>Best For</th><th>Sensor Packages</th><th>Monthly Platform</th><th>Integration</th></tr></thead><tbody><tr><td>John Deere Ops</td><td>JD equipment users</td><td>Bundled</td><td>$50+</td><td>Deep JD</td></tr><tr><td>FarmBeats</td><td>Flexible IoT</td><td>$500+</td><td>Azure usage</td><td>Excellent</td></tr><tr><td>Farmio</td><td>Easy deployment</td><td>$1,000+</td><td>$29</td><td>Good</td></tr><tr><td>OnFarm</td><td>Multi-sensor</td><td>$2,000+</td><td>$99</td><td>Excellent</td></tr><tr><td>Sensoterra</td><td>Soil moisture</td><td>$300/sensor</td><td>$20</td><td>Moderate</td></tr></tbody></table><h2>Essential IoT Sensors for Agriculture</h2><p>Key sensor types for farming operations:</p><ul><li><strong>Soil Sensors:</strong> Moisture, temperature, and nutrient monitoring.</li><li><strong>Weather Stations:</strong> Temperature, humidity, rainfall, wind measurement.</li><li><strong>Crop Sensors:</strong> Growth monitoring and stress detection.</li><li><strong>Equipment Telematics:</strong> Performance, location, and maintenance tracking.</li><li><strong>Storage Sensors:</strong> Temperature and humidity in grain bins and warehouses.</li></ul><h2>IoT Implementation Benefits</h2><p>Agricultural IoT delivers measurable benefits:</p><ul><li><strong>Data-Driven Decisions:</strong> Real-time information replaces guesswork.</li><li><strong>Automation:</strong> Automated responses to sensor triggers.</li><li><strong>Efficiency:</strong> Optimized resource use based on actual conditions.</li><li><strong>Risk Reduction:</strong> Early warnings prevent losses.</li><li><strong>Documentation:</strong> Comprehensive records for compliance and analysis.</li></ul><h2>Emerging IoT Trends</h2><p>Agricultural IoT continues to advance:</p><ul><li><strong>5G Connectivity:</strong> Faster data transmission enables real-time control.</li><li><strong>Edge Computing:</strong> On-field processing reduces latency.</li><li><strong>AI Integration:</strong> Machine learning improves sensor data analysis.</li><li><strong>Autonomous Systems:</strong> IoT controls autonomous equipment.</li><li><strong>Satellite Integration:</strong> Ground sensors complement satellite monitoring.</li></ul><h2>Conclusion</h2><p>Agricultural IoT platforms enable comprehensive monitoring and automation for modern farming. John Deere Operations Center excels for equipment integration, FarmBeats offers flexible Azure-based IoT, and Farmio provides easy-to-deploy sensor packages. The right choice depends on existing equipment, data infrastructure, and automation needs.</p>",
  "seo_keywords": [
    "agricultural IoT",
    "farm sensors",
    "smart farming technology",
    "precision agriculture IoT",
    "connected farming"
  ],
  "slug": "agricultural-iot-platforms-2026",
  "published_at": "2026-05-01",
  "author": "Agriculture Tech Team",
  "language": "en-US",
  "canonical_link": "https://www.housecar.life/posts/agricultural-iot-platforms-2026",
  "alternate_links": {
    "en-US": "https://www.housecar.life/posts/agricultural-iot-platforms-2026",
    "zh-CN": "https://www.housecar.life/posts/zh/agricultural-iot-platforms-2026"
  }
}