{
  "slug": "best-construction-site-security-access-control-systems-2026",
  "published_at": "2026-05-01",
  "author": "Construction Security Expert",
  "title": "Best Construction Site Security and Access Control Systems for Contractors - 2026 Review",
  "description": "Comprehensive review of site security platforms including SecurityPro, AccessControlManager, and construction security systems for contractor site protecti",
  "content": "<h1>Best Construction Site Security and Access Control Systems for Contractors</h1><p>Construction site security and access control systems have become essential for contractors managing site protection, coordinating access management, and integrating security workflows with project management. These specialized platforms enable systematic security management that ensures site safety while enabling access coordination.</p><h2>Background: Site Security Challenges</h2><p>Construction sites require systematic security including access control, surveillance management, and protection coordination. Security management affects site safety and asset protection. Traditional management using manual methods creates coordination gaps and security risks.</p><p>Access control involves systematic site entry management with authorization, tracking, and credential coordination. Control quality affects site security and worker safety. Professional security platforms address control through systematic access management.</p><p>Surveillance coordination requires systematic monitoring with documentation, alerting, and compliance tracking. Coordination quality affects protection effectiveness and incident response. Professional platforms support coordination through systematic surveillance management.</p><h2>Deep Review: Leading Security Platforms</h2><h3>SecurityPro: Construction Security Platform</h3><p>SecurityPro delivers security management with access control, surveillance coordination, and protection management. The platform serves contractors requiring comprehensive security management.</p><p>SecurityPro's access features enable systematic site entry management with authorization and tracking coordination. Surveillance features manage monitoring with documentation and alerting management. Protection features coordinate site security with incident response.</p><p>Authorization features manage credentials with verification and access tracking. Incident features coordinate security events with documentation and response management. Reporting delivers security visibility with access metrics and protection status.</p><h3>AccessControlManager: Site Entry System</h3><p>AccessControlManager provides security functionality emphasizing access coordination, entry tracking, and protection management. The platform serves contractors requiring systematic access control.</p><p>AccessControlManager's access features enable comprehensive site entry management with authorization and tracking coordination. Entry features manage credentials with verification and access tracking. Protection features coordinate site security with incident management.</p><p>Coordination features coordinate access control with operational scheduling. Authorization features manage credentials with verification tracking. Reporting delivers access visibility with entry metrics and protection analysis.</p><h3>Integrated Security Systems</h3><p>Integrated security platforms deliver management functionality connected with comprehensive project management systems. These platforms enable seamless connection between security and project workflows.</p><p>Integrated security features enable systematic protection management with project integration and access coordination. Project integration connects security with operational workflows and site management. Access integration connects security with entry authorization and credential management.</p><p>Surveillance integration connects security with monitoring and alerting coordination. Incident integration connects security with event response and documentation management. The platform's comprehensive project context provides operational visibility alongside security management.</p><h2>Parameter Comparison Table</h2><table><thead><tr><th>Feature</th><th>SecurityPro</th><th>AccessControlManager</th><th>Integrated Security</th><th>Best For</th></tr></thead><tbody><tr><td>Platform Focus</td><td>Security management</td><td>Access control</td><td>Integrated system</td><td>Primary purpose</td></tr><tr><td>Starting Price</td><td>$299/month</td><td>$199/month</td><td>Part of platform</td><td>Cost structure</td></tr><tr><td>Access Features</td><td>Comprehensive</td><td>Comprehensive</td><td>Comprehensive</td><td>Site entry</td></tr><tr><td>Surveillance Features</td><td>Comprehensive</td><td>Good</td><td>Comprehensive</td><td>Monitoring management</td></tr><tr><td>Protection Features</td><td>Comprehensive</td><td>Comprehensive</td><td>Comprehensive</td><td>Security coordination</td></tr><tr><td>Authorization Features</td><td>Comprehensive</td><td>Comprehensive</td><td>Comprehensive</td><td>Credential management</td></tr><tr><td>Incident Features</td><td>Comprehensive</td><td>Available</td><td>Comprehensive</td><td>Event response</td></tr><tr><td>Alerting Features</td><td>Comprehensive</td><td>Good</td><td>Comprehensive</td><td>Notification management</td></tr><tr><td>Integration Features</td><td>Comprehensive</td><td>Good</td><td>Comprehensive</td><td>Workflow connection</td></tr><tr><td>Credential Integration</td><td>Comprehensive</td><td>Comprehensive</td><td>Comprehensive</td><td>Authorization connection</td></tr><tr><td>Camera Integration</td><td>Comprehensive</td><td>Available</td><td>Comprehensive</td><td>Surveillance connection</td></tr><tr><td>Reporting</td><td>Comprehensive</td><td>Comprehensive</td><td>Good</td><td>Analytics</td></tr></tbody></table><h2>Essential Security Systems Selection Criteria</h2><p>Selecting construction security software requires evaluation of access needs, surveillance requirements, and integration priorities:</p><p><strong>Access Features:</strong> Site entry determines security control. Evaluate access features, authorization capabilities, and tracking management.</p><p><strong>Surveillance Features:</strong> Monitoring management determines protection visibility. Evaluate surveillance features, documentation capabilities, and alerting coordination.</p><p><strong>Protection Features:</strong> Security coordination determines site safety. Evaluate protection features, incident capabilities, and response management.</p><p><strong>Authorization Features:</strong> Credential management determines access control. Evaluate authorization features, verification capabilities, and tracking coordination.</p><p><strong>Integration Requirements:</strong> System connection determines workflow efficiency. Evaluate project integration, credential connection, and surveillance linkage.</p><h2>Trend Predictions for Security Technology</h2><p>Construction security technology will advance significantly through 2026, incorporating AI-powered surveillance analysis, automated access coordination, and predictive security analysis:</p><p><strong>AI-Powered Surveillance Analysis:</strong> Machine learning will automatically analyze surveillance footage for security events, improving monitoring without manual observation. This capability improves surveillance quality.</p><p><strong>Automated Access Coordination:</strong> Systems will automatically coordinate site access based on schedules and authorization levels, improving control without manual configuration. This automation improves access management.</p><p><strong>Predictive Security Analysis:</strong> Advanced analytics will forecast security risks based on site conditions and historical patterns, enabling proactive protection. This capability improves planning accuracy.</p><p><strong>Real-Time Security Monitoring:</strong> Continuous tracking will provide instant visibility into site security without manual observation, improving coordination awareness. This capability improves security management.</p><p><strong>Integrated Protection Intelligence:</strong> Complete integration with site systems will enable comprehensive security coordination across construction workflows. This integration improves security management.</p><p>Contractors selecting security software in 2026 should prioritize platforms demonstrating commitment to these advancing capabilities while delivering reliable core functionality for current security management needs. Effective security management ensures protection, enables access control, and supports site safety.</p>",
  "seo_keywords": [
    "construction site security",
    "access control",
    "SecurityPro",
    "AccessControlManager",
    "site protection",
    "security systems",
    "construction security",
    "site access",
    "security management"
  ],
  "language": "en-US",
  "canonical_link": "https://www.housecar.life/posts/best-construction-site-security-access-control-systems-2026",
  "alternate_links": {
    "en-US": "https://www.housecar.life/posts/best-construction-site-security-access-control-systems-2026",
    "zh-CN": "https://www.housecar.life/zh/posts/best-construction-site-security-access-control-systems-2026"
  }
}