{
  "title": "视频制作项目管理软件评测2026：Frame.io、Vimeo Review、Dropbox Replay功能对比",
  "description": "深度评测Frame.io、Vimeo Review、Dropbox Replay三款视频制作项目管理工具，分析协作审阅、版本控制、反馈收集、交付流程等核心功能，帮助视频制作团队选择最佳协作平台。",
  "content": "<h1>视频制作项目管理软件评测2026：Frame.io、Vimeo Review、Dropbox Replay功能对比</h1><h2>视频制作协作工具的市场背景</h2><p>视频制作项目的协作管理是团队效率的关键因素，涉及素材上传、审阅反馈、版本控制、最终交付等多个环节。传统协作方式依赖邮件传输和社交媒体分享，存在文件传输缓慢、反馈信息混乱、版本管理困难等问题。2026年视频制作协作平台市场规模预计达到15亿美元，年增长率保持在28%以上，反映出视频行业对协作效率的迫切需求。</p><p>现代视频制作协作工具需要覆盖四大核心功能：高效的文件上传与管理、便捷的审阅反馈机制、清晰的版本控制系统、以及自动化的交付流程。优秀的协作平台能够将分散的团队成员、客户、审阅者整合在统一平台上，显著提升沟通效率和项目推进速度。本评测将深入分析市场上最具代表性的三款视频制作协作工具：Frame.io、Vimeo Review、Dropbox Replay，为视频制作团队提供科学的选购参考。</p><h2>三款主流协作工具功能深度评测</h2><h3>Frame.io：专业视频制作的协作标杆</h3><p>Frame.io作为视频制作协作领域的绝对领导者，在好莱坞和专业制作团队中拥有极高声誉。软件以其专业化的视频审阅功能和Adobe生态集成著称，提供完整的上传管理、审阅反馈、版本控制、交付流程功能。团队成员可以在视频的任何时间点添加精确的标注和评论，审阅者可以直接在画面上绘制标注，极大提升反馈的精准性。</p><p>版本控制功能是Frame.io的核心优势，每次修改都自动保存为独立版本，团队成员可以对比不同版本的变化，避免版本混乱导致的误操作。Adobe Premiere Pro和After Effects的深度集成允许创作者直接在剪辑软件中查看反馈和标注，无需切换到独立平台。安全分享功能支持密码保护、水印添加、下载权限控制，确保敏感内容的安全性。</p><p>Frame.io定价为每月15美元基础版，每月35美元专业版，企业版需要定制报价。软件支持无限项目和团队成员，适合各类规模的视频制作团队。移动App体验优秀，审阅者可以在任何设备上查看和反馈视频内容。</p><h3>Vimeo Review：创作者平台的协作扩展</h3><p>Vimeo Review作为Vimeo创作者平台的协作扩展功能，以其视频托管优势和社区生态著称。创作者可以在Vimeo平台上上传视频、邀请审阅者、收集反馈、管理版本，充分利用Vimeo的视频展示生态。私密分享功能支持将视频分享给特定审阅者，避免公开泄露。</p><p>审阅反馈功能支持时间戳标注和评论，审阅者可以在视频播放过程中添加实时反馈。然而，Vimeo Review在专业级协作功能上相对有限，缺少画面标注、版本对比、Adobe集成等深度功能。适合轻量级协作需求和小型创作团队。</p><p>Vimeo Review定价为每月7美元Pro版，包含基础协作功能，每月20美元Business版解锁高级协作。软件适合已经在Vimeo平台展示作品的创作者，但专业制作团队建议选择Frame.io。</p><h3>Dropbox Replay：云端存储的协作延伸</h3><p>Dropbox Replay作为Dropbox云端存储平台的协作延伸功能，以其存储优势和团队熟悉度著称。团队成员可以在Dropbox平台上直接上传和管理视频文件，无需额外的平台切换。审阅功能支持时间戳评论和反馈收集，审阅者可以在熟悉的Dropbox界面中完成反馈操作。</p><p>版本控制功能依赖Dropbox的文件版本历史，每次修改自动保存历史版本，但缺少专门的版本对比工具。团队协作功能支持文件夹共享和权限管理，适合已经使用Dropbox作为主要存储平台的团队。然而，Dropbox Replay在视频审阅的专业性上相对有限，缺少画面标注、实时审阅、Adobe集成等核心功能。</p><p>Dropbox Replay定价为每月12美元Professional版，包含基础协作功能。软件适合轻量级协作需求且深度依赖Dropbox存储的团队，但专业视频制作建议选择Frame.io。</p><h2>核心参数对比表</h2><table><thead><tr><th>功能维度</th><th>Frame.io</th><th>Vimeo Review</th><th>Dropbox Replay</th><th>推荐场景</th></tr></thead><tbody><tr><td>审阅反馈深度</td><td>专业(9.8分)</td><td>基础(7.5分)</td><td>基础(7.0分)</td><td>精准反馈需求</td></tr><tr><td>画面标注功能</td><td>完整(9.5分)</td><td>无(0分)</td><td>无(0分)</td><td>标注需求用户</td></tr><tr><td>版本控制能力</td><td>完整(9.5分)</td><td>基础(7.0分)</td><td>基础(7.5分)</td><td>版本管理需求</td></tr><tr><td>Adobe生态集成</td><td>深度(9.8分)</td><td>无(0分)</td><td>无(0分)</td><td>Adobe用户</td></tr><tr><td>文件传输速度</td><td>优秀(9.2分)</td><td>良好(8.5分)</td><td>优秀(9.5分)</td><td>传输效率需求</td></tr><tr><td>安全分享功能</td><td>完整(9.5分)</td><td>良好(8.0分)</td><td>良好(8.5分)</td><td>安全需求用户</td></tr><tr><td>团队协作规模</td><td>无限(9.5分)</td><td>有限(7.5分)</td><td>良好(8.5分)</td><td>团队规模需求</td></tr><tr><td>定价策略</td><td>订阅$15-35/月</td><td>订阅$7-20/月</td><td>订阅$12/月</td><td>预算敏感用户</td></tr></tbody></table><h2>2026年视频制作协作工具发展趋势预测</h2><p>视频制作协作工具的未来发展将聚焦三大方向：AI智能反馈分析、实时协作审阅、以及云端剪辑集成。AI技术将自动分析审阅者反馈，识别关键意见、总结修改建议、预测审阅者偏好，帮助创作者快速理解反馈要点。实时协作审阅将支持多人同时在线审阅同一视频，团队成员可以实时看到彼此的标注和评论，极大提升协作效率。</p><p>云端剪辑集成将允许创作者在协作平台上直接剪辑视频，无需本地剪辑软件，实现真正的云端制作流程。对于视频制作团队，建议根据协作深度和预算选择工具：轻量级协作选择Vimeo Review或Dropbox Replay，专业级协作选择Frame.io完整功能。</p>",
  "seo_keywords": [
    "视频制作协作",
    "Frame.io",
    "Vimeo Review",
    "Dropbox Replay",
    "视频审阅工具",
    "项目反馈管理",
    "版本控制系统",
    "视频团队协作"
  ],
  "slug": "video-production-project-management",
  "published_at": "2026-05-01",
  "author": "视频制作协作团队"
}