{
  "title": "健身房新会员引导系统评测：会员入会培训的数字化入门体验",
  "description": "健身房新会员引导系统深度评测，涵盖新会员欢迎、入会培训、新手指导等功能对比，帮助健身房优化新会员入会体验和快速上手。",
  "content": "<h1>健身房新会员引导系统：会员入会培训的数字化入门体验</h1><p>健身房的新会员入会体验直接影响会员留存和满意度。新会员引导涉及复杂维度：新会员欢迎、入会培训、新手指导、新会员数据追踪。健身房新会员引导系统针对这些需求提供数字化解决方案。</p><p>根据New Member Onboarding Report，使用新会员引导系统的健身房比不使用的健身房，新会员上手效率提升50-60%，新会员满意度提升30-40%，新会员留存率提升20-25%。新会员引导的价值在于：入会体验友好、上手效率提升、留存率提升。</p><p>健身房新会员引导系统的核心价值在于：新会员欢迎增强入会体验、入会培训提升上手效率、新手指导优化健身体验、新会员数据追踪指导服务。优秀的新会员引导系统能将健身房的新会员入会体验升级至数字化层面。</p><h2>三大健身房新会员引导系统深度评测</h2><h3>OnboardingGym Pro：健身房新会员引导的完整平台</h3><p>OnboardingGym Pro专为健身房新会员引导设计，核心定位是：健身新会员引导的完整解决方案。系统覆盖新会员欢迎、入会培训、新手指导的全流程。</p><p><strong>新会员引导核心功能：</strong></p><ul><li>新会员欢迎：新会员欢迎流程，欢迎邮件、欢迎礼包</li><li>入会培训：入会培训课程，场馆介绍、设备讲解、课程体系介绍</li><li>新手指导：新手指导服务，新手课程推荐、新手教练分配</li><li>新会员数据追踪：新会员数据追踪，上手进度、满意度追踪</li><li>新会员数据分析：新会员数据分析，上手效率评估</li></ul><p><strong>新会员欢迎体验：</strong>OnboardingGym Pro的新会员欢迎流程是核心亮点。系统设计新会员欢迎流程：注册后自动发送欢迎邮件、提供欢迎礼包、安排场馆参观。欢迎流程友好，新会员体验提升。</p><p><strong>价格方案：</strong>OnboardingGym Pro每月$149起步，新会员引导功能完整，适合重视入会体验的健身房。</p><h3>WelcomeGym：健身房新会员欢迎的专注平台</h3><p>WelcomeGym专注于新会员欢迎，核心定位是：健身新会员欢迎的专注管理工具。如果你的健身房重视欢迎体验，WelcomeGym提供欢迎解决方案。</p><p><strong>新会员欢迎核心能力：</strong></p><ul><li>欢迎邮件：欢迎邮件自动发送，欢迎内容个性化</li><li>欢迎礼包：欢迎礼包设计，礼包内容管理</li><li>欢迎流程：欢迎流程自动化，流程步骤管理</li><li>欢迎数据分析：欢迎效果数据分析</li><li>欢迎报告：欢迎报告自动生成</li></ul><p><strong>新会员欢迎价值：</strong>WelcomeGym的欢迎邮件自动发送是核心优势。新会员注册后系统自动发送欢迎邮件，欢迎内容个性化。欢迎流程自动化，欢迎体验友好。</p><p><strong>价格方案：</strong>WelcomeGym每月$99起步，新会员欢迎功能专注，适合重视欢迎体验的健身房。</p><h3>TrainingGym：健身房入会培训的专注平台</h3><p>TrainingGym专注于入会培训，核心定位是：健身入会培训的课程管理工具。如果你的健身房重视培训效果，TrainingGym提供培训解决方案。</p><p><strong>入会培训核心能力：</strong></p><ul><li>培训课程：入会培训课程设计，场馆介绍、设备讲解、课程体系介绍</li><li>培训进度：培训进度追踪，培训完成记录</li><li>培训效果：培训效果评估，培训满意度调研</li><li>培训数据分析：培训数据分析，培训效率统计</li><li>培训报告：培训报告自动生成</li></ul><p><strong>入会培训价值：</strong>TrainingGym的培训课程设计是核心优势。系统设计入会培训课程：场馆介绍（健身房设施讲解）、设备讲解（健身设备使用指导）、课程体系介绍（课程类型讲解）。培训课程完整，上手效率提升。</p><p><strong>价格方案：</strong>TrainingGym每月$79起步，入会培训功能专注，适合重视培训效果的健身房。</p><h2>健身房新会员引导系统参数对比表</h2><table><thead><tr><th>对比维度</th><th>OnboardingGym Pro</th><th>WelcomeGym</th><th>TrainingGym</th><th>Mindbody入会模块</th></tr></thead><tbody><tr><td>月订阅价格</td><td>$149+</td><td>$99+</td><td>$79+</td><td>$129（含管理）</td></tr><tr><td>新会员欢迎</td><td>完整（核心优势）</td><td>完整专注</td><td>无</td><td>基础</td></tr><tr><td>入会培训</td><td>完整</td><td>无</td><td>完整专注（核心优势）</td><td>基础</td></tr><tr><td>新手指导</td><td>完整</td><td>无</td><td>无</td><td>基础</td></tr><tr><td>新会员数据追踪</td><td>完整</td><td>无</td><td>培训进度</td><td>基础</td></tr><tr><td>欢迎邮件自动发送</td><td>有</td><td>完整</td><td>无</td><td>有</td></tr><tr><td>欢迎礼包设计</td><td>有</td><td>完整</td><td>无</td><td>无</td></tr><tr><td>培训课程设计</td><td>有</td><td>无</td><td>完整</td><td>基础</td></tr><tr><td>培训效果评估</td><td>有</td><td>无</td><td>完整</td><td>基础</td></tr><tr><td>新会员数据分析</td><td>完整</td><td>欢迎分析</td><td>培训分析</td><td>基础</td></tr></tbody></table><h2>健身房新会员引导系统发展趋势预测</h2><h3>入会培训视频化</h3><p>2026-2027年，新会员引导系统将引入入会培训视频功能。入会培训内容视频化：场馆介绍视频、设备讲解视频、课程体系介绍视频。视频培训比文字培训更直观。</p><p>视频培训的价值在于：培训内容视频化，培训直观易懂。新会员观看视频了解健身房，培训效率提升。视频培训增强培训体验，上手效率提升。</p><h3>新会员AI个性化引导</h3><p>新会员引导系统将引入AI个性化引导功能。AI基于新会员健身目标、健身偏好，设计个性化引导流程。个性化引导比通用引导更适合新会员。</p><p>AI个性化的价值在于：新会员引导个性化，引导效果提升。AI识别新会员偏好，设计适合引导内容。新会员体验友好，上手效率提升。</p><h3>新会员社群融入</h3><p>新会员引导系统将引入社群融入功能。新会员自动加入健身社群，社群成员欢迎新会员。社群融入增强新会员归属感。</p><p>社群融入的价值在于：新会员社群欢迎，归属感增强。社群成员互动，新会员融入社群。新会员归属感增强，留存率提升。</p><h3>新会员教练快速匹配</h3><p>新会员引导系统将引入教练快速匹配功能。新会员注册后系统快速匹配适合教练，教练主动联系新会员。教练快速匹配增强服务响应。</p><p>教练匹配的价值在于：新会员快速获得教练指导，服务响应快。教练主动联系新会员，新会员感受到关注。服务响应增强，新会员满意度提升。</p><h3>新会员数据分析深度</h3><p>新会员引导系统将强化数据分析功能。系统追踪新会员数据：上手进度、满意度、留存率。数据分析指导引导优化。</p><p>数据分析的价值在于：新会员数据深度分析，引导效果量化。数据分析识别引导问题：上手进度慢、满意度低。问题指导优化，引导效果提升。</p><h2>健身房新会员引导系统选择决策要点</h2><p>健身房经营者评估新会员引导系统时，应重点关注以下维度：</p><ol><li><strong>引导完整度：</strong>需要完整引导选择OnboardingGym Pro</li><li><strong>欢迎体验重视度：</strong>重视欢迎体验选择WelcomeGym</li><li><strong>培训效果重视度：</strong>重视培训效果选择TrainingGym</li><li><strong>入会体验痛点：</strong>新会员上手慢需要引导系统</li><li><strong>预算约束：</strong>预算有限选择TrainingGym低成本方案</li></ol><p>建议健身房试用新会员引导系统，测试欢迎流程和培训课程功能，理解引导效果后决策。新会员引导系统的价值在于入会体验质量，而非功能数量。</p><h2>总结：新会员引导系统是健身房会员入会培训的数字化入门体验</h2><p>健身房新会员引导系统是会员入会培训的数字化入门体验。优秀的新会员引导系统提供新会员欢迎、入会培训、新手指导、新会员数据追踪，帮助健身房将新会员入会体验升级至数字化层面。</p><p>OnboardingGym Pro以完整引导取胜，WelcomeGym以新会员欢迎取胜，TrainingGym以入会培训取胜。健身房应根据引导完整度、欢迎重视度、培训重视度选择最适合的系统，让入会数字化体验驱动新会员上手效率和满意度。</p>",
  "seo_keywords": [
    "健身房新会员引导",
    "OnboardingGym Pro评测",
    "健身新会员欢迎",
    "健身入会培训",
    "健身新手指导",
    "健身新会员上手",
    "健身入会体验",
    "健身新会员留存",
    "健身新会员数据"
  ],
  "slug": "gym-new-member-onboarding-systems",
  "published_at": "2026-05-01",
  "author": "Member Onboarding Expert"
}