{
  "title": "船舶租赁客户体验平台评测：提升服务质量的数字化工具",
  "description": "全面评测2026年主流船舶租赁客户体验平台，包括MarineCX、BoatExperiencePro、YachtService等系统的客户反馈、服务管理与体验优化功能。",
  "content": "<h1>船舶租赁客户体验平台评测：提升服务质量的数字化工具</h1><h2>行业背景与客户体验挑战</h2><p>客户体验是船舶租赁企业长期竞争力的关键因素。游艇租赁属于高价值服务消费，客户对体验质量期望高。客户体验涉及预订体验、航行体验、服务体验、后访体验等多个环节。传统客户体验管理依赖事后评价和人工处理，难以实时跟踪体验、及时处理问题、系统优化服务。</p><p>船舶租赁客户体验平台的核心价值在于系统化体验管理。专业系统提供客户反馈收集、实时体验监控、服务问题处理、体验数据分析、服务优化建议等功能。优秀的体验平台帮助企业及时发现体验问题，快速响应客户需求，系统优化服务质量，提升客户满意度和忠诚度。</p><p>2026年的船舶租赁客户体验管理市场呈现专业化趋势。通用客户体验软件虽可处理基础反馈，但缺乏船舶租赁行业针对性。专业体验平台叠加行业特有体验环节、服务场景、反馈内容等。本文将深度评测主流专业平台。</p><h2>核心平台评测</h2><h3>MarineCX：行业领先的客户体验平台</h3><p>MarineCX是全球领先的船舶租赁客户体验管理软件，创立于2019年，总部位于美国迈阿密。系统定位为行业专属体验管理平台，覆盖反馈收集、实时监控、服务管理、体验分析等核心功能。截至2026年，MarineCX服务超过150家游艇租赁企业。</p><p>MarineCX的核心优势在于多渠道反馈收集功能。系统通过邮件、短信、App、网站等多渠道收集客户反馈。反馈内容覆盖预订体验、船只体验、服务体验、整体满意度等。反馈时机智能选择，在租赁关键节点触发反馈请求。反馈自动化处理，减少人工工作。</p><p>系统的实时体验监控功能完善。租赁过程中实时收集体验数据，及时发现问题。体验预警功能提醒低评分体验，触发干预。问题自动通知相关团队处理。实时监控帮助企业快速响应体验问题。</p><p>MarineCX的服务管理功能专业实用。服务请求记录、任务分配、进度跟踪、完成确认等功能完善。服务时效管理确保及时响应。服务质量评估帮助企业优化服务。服务数据分析识别服务薄弱环节。</p><p>定价方面，MarineCX采取分层订阅模式。基础版月费149美元，支持最多2000个客户反馈；标准版月费299美元，支持1万个反馈；专业版月费499美元，支持无限反馈和实时监控。</p><h3>BoatExperiencePro：轻量级客户体验工具</h3><p>BoatExperiencePro成立于2021年，总部位于加州洛杉矶，定位为轻量级船舶租赁客户体验工具。系统专为小型游艇租赁企业设计，核心功能聚焦反馈收集和基础统计。BoatExperiencePro目前服务超过200家小型企业。</p><p>BoatExperiencePro的核心特点是简洁易用。系统界面直观简洁，功能模块清晰。用户无需培训即可快速上手。</p><p>系统的反馈收集功能覆盖小型企业需求。邮件反馈收集简易。基础反馈统计清晰展示满意度。</p><p>定价方面，BoatExperiencePro采取极简定价策略。单一套餐月费59美元，包含反馈收集和统计。系统提供免费试用。</p><h3>YachtService：中型企业客户体验软件</h3><p>YachtService创立于2020年，总部位于英国伦敦，定位为中型游艇租赁企业的专业客户体验软件。系统功能覆盖反馈收集、服务管理、体验分析等核心模块。YachtService目前服务50余家中型企业。</p><p>YachtService的核心优势在于功能平衡。系统精准匹配中型企业需求，覆盖核心体验流程，保持易用性。</p><p>系统的反馈收集功能完善。多渠道反馈、反馈分析等功能覆盖。</p><p>定价方面，YachtService采取分层订阅模式。基础版月费99美元；标准版月费199美元；专业版月费349美元。</p><h2>功能对比</h2><table><thead><tr><th>功能维度</th><th>MarineCX</th><th>BoatExperiencePro</th><th>YachtService</th></tr></thead><tbody><tr><td>反馈收集</td><td>多渠道</td><td>邮件收集</td><td>完善收集</td></tr><tr><td>实时监控</td><td>完善监控</td><td>无</td><td>基础监控</td></tr><tr><td>服务管理</td><td>完善管理</td><td>无</td><td>基础管理</td></tr><tr><td>体验分析</td><td>深度分析</td><td>基础统计</td><td>完善分析</td></tr><tr><td>问题处理</td><td>自动处理</td><td>无</td><td>基础处理</td></tr><tr><td>移动端</td><td>完善App</td><td>基础查看</td><td>良好App</td></tr><tr><td>适用企业</td><td>中型+</td><td>小微</td><td>中型</td></tr><tr><td>基础价格</td><td>149美元/月</td><td>59美元/月</td><td>99美元/月</td></tr></tbody></table><h2>趋势预测</h2><p>船舶租赁客户体验平台将向实时化、智能化方向发展。实时体验监控将更精准捕捉体验问题。AI体验分析将自动识别体验改进机会。预测性体验管理将预测客户体验风险提前干预。体验与其他系统将深度集成，实现体验驱动的服务优化。未来平台将更专注于体验质量持续提升。</p>",
  "seo_keywords": [
    "船舶租赁客户体验",
    "MarineCX",
    "BoatExperiencePro",
    "YachtService",
    "游艇客户满意度",
    "船舶服务管理",
    "游艇反馈收集",
    "海事客户体验",
    "船只服务质量",
    "游艇体验优化"
  ],
  "slug": "boat-rental-customer-experience-platform-review",
  "published_at": "2026-05-01",
  "author": "Marine CX Specialist"
}