{
  "slug": "manufacturing-dashboard-reporting-review-2026",
  "category": "manufacturing-production-tools",
  "title": "制造仪表盘报表系统深度评测：SAP Dashboard vs Power BI Manufacturing Dashboard vs Tableau Manufacturing 2026对比",
  "description": "全面对比2026年三大制造仪表盘报表系统SAP Dashboard、Power BI Manufacturing Dashboard和Tableau Manufacturing，从仪表盘可视化、报表分析、实时监控到数据呈现深度剖析，帮助制造企业选择最适合的仪表盘报表解决方案。了解更多功能和价格对比，找到最适合.",
  "seo_keywords": [
    "制造仪表盘报表系统",
    "SAP Dashboard",
    "Power BI Manufacturing Dashboard",
    "Tableau Manufacturing",
    "仪表盘可视化软件",
    "报表分析系统",
    "实时监控仪表盘",
    "数据呈现工具",
    "制造仪表盘",
    "生产报表系统"
  ],
  "published_at": "2026-05-01",
  "author": "王志华 - 仪表盘报表专家",
  "content": "<h2>HouseCar 自由观点：灵活办公的诗意</h2><p>每分钟节省，是生命在路上的延伸。工具解放创业者，去追逐房车自由。HouseCar：工具赋能，生活自由。别让报表困住灵魂，把时间还给家人、自然。灵活办公，是选择。</p>\n\n<h2>背景介绍</h2><p>仪表盘报表是制造企业数据可视化和决策支持的核心功能，直接影响数据呈现、管理决策和生产监控。传统制造企业仪表盘报表依赖手工制作、报表更新滞后、数据可视化困难，平均报表制作周期长达数天，决策支持不准确。研究表明，部署仪表盘报表系统后，报表制作周期缩短至实时，仪表盘自动化、数据可视化实时化。本文深度对比SAP Dashboard、Power BI Manufacturing Dashboard和Tableau Manufacturing三大制造仪表盘报表系统，帮助制造企业做出明智的仪表盘报表软件选型决策。</p><h2>核心功能对比</h2><table><thead><tr><th>功能模块</th><th>SAP Dashboard</th><th>Power BI Manufacturing Dashboard</th><th>Tableau Manufacturing</th><th>对比分析</th></tr></thead><tbody><tr><td>仪表盘可视化</td><td>仪表盘可视化强大</td><td>仪表盘可视化最强大</td><td>仪表盘可视化最强大</td><th>Power BI/Tableau仪表盘最强</th></tr><tr><td>报表分析</td><td>报表分析最强大</td><td>报表分析强大</td><td>报表分析强大</td><th>三者报表分析均完善</th></tr><tr><td>实时监控</td><td>实时监控最强大</td><td>实时监控强大</td><td>实时监控功能</td><th>SAP实时监控最强大</th></tr><tr><td>数据呈现</td><td>数据呈现强大</td><td>数据呈现最强大</td><td>数据呈现最强大</td><th>Power BI/Tableau数据呈现最强</th></tr><tr><td>交互仪表盘</td><td>交互仪表盘强大</td><td>交互仪表盘最强大</td><td>交互仪表盘最强大</td><th>Power BI/Tableau交互仪表盘最强</th></tr><tr><td>报表模板</td><td>报表模板最强大</td><td>报表模板强大</td><td>报表模板强大</td><th>三者报表模板均完善</th></tr><tr><td>移动仪表盘</td><td>移动仪表盘强大</td><td>移动仪表盘最强大</td><td>移动仪表盘强大</td><th>Power BI移动仪表盘最强大</th></tr><tr><td>成本</td><td>年许可费中等</td><td>性价比高</td><td>年许可费中等</td><th>Power BI性价比最高</th></tr></tbody></table><h2>SAP Dashboard制造仪表盘报表系统深度评测</h2><p>SAP Dashboard是SAP仪表盘报表模块，与SAP ERP无缝集成形成完整的仪表盘报表价值链。仪表盘可视化强大功能可视化仪表盘、仪表盘图表、仪表盘设计。报表分析最强大功能分析报表、报表数据、报表统计，报表分析最深入。实时监控最强大功能实时监控仪表盘、实时更新仪表盘数据、实时预警仪表盘异常。数据呈现强大功能呈现数据、数据图表、数据可视化。交互仪表盘强大功能交互仪表盘、仪表盘交互操作。报表模板最强大功能提供报表模板、报表模板库。移动仪表盘强大功能提供移动仪表盘、移动仪表盘访问。年许可费中等功能年许可费从8万美元起，适合已部署SAP ERP的制造企业。SAP Dashboard的年许可费从8万美元起，适合已部署SAP ERP的制造企业。</p><ul><li><strong>报表分析最强大</strong>: 报表数据统计分析</li><li><strong>SAP ERP集成</strong>: ERP仪表盘报表协同</li><li><strong>实时监控最强大</strong>: 仪表盘实时监控预警</li><li><strong>报表模板最强大</strong>: 报表模板库丰富</li><li><strong>适合SAP企业</strong>: 已部署SAP ERP</li></ul><h2>Power BI Manufacturing Dashboard制造仪表盘报表系统评测</h2><p>Power BI Manufacturing Dashboard是微软Power BI制造仪表盘解决方案，提供最强大的仪表盘可视化和性价比优势。仪表盘可视化最强大功能可视化仪表盘、仪表盘图表、仪表盘设计，仪表盘可视化最丰富。报表分析强大功能分析报表、报表数据。实时监控强大功能实时监控仪表盘。数据呈现最强大功能呈现数据、数据图表、数据可视化，数据呈现最丰富。交互仪表盘最强大功能交互仪表盘、仪表盘交互操作，交互仪表盘最智能。报表模板强大功能提供报表模板。移动仪表盘最强大功能提供移动仪表盘、移动仪表盘访问。性价比最高功能年许可费从3万美元起，是性价比最高的仪表盘报表方案。Power BI Manufacturing Dashboard的年许可费从3万美元起，适合年营收500万至5000万美元的制造企业。</p><ul><li><strong>仪表盘可视化最强大</strong>: 仪表盘图表设计丰富</li><li><strong>数据呈现最强大</strong>: 数据图表可视化丰富</li><li><strong>交互仪表盘最强大</strong>: 仪表盘交互操作智能</li><li><strong>性价比最高</strong>: 年许可费3万美元起</li><li><strong>适合中小企业</strong>: 年营收500万至5000万美元</li></ul><h2>Tableau Manufacturing制造仪表盘报表系统评测</h2><p>Tableau Manufacturing是仪表盘报表领域的领先解决方案，提供最强大的仪表盘可视化和数据呈现。仪表盘可视化最强大功能可视化仪表盘、仪表盘图表、仪表盘设计，仪表盘可视化最专业。报表分析强大功能分析报表、报表数据。实时监控功能实时监控仪表盘。数据呈现最强大功能呈现数据、数据图表、数据可视化，数据呈现最专业。交互仪表盘最强大功能交互仪表盘、仪表盘交互操作。报表模板强大功能提供报表模板。移动仪表盘强大功能提供移动仪表盘。年许可费中等功能年许可费从6万美元起，适合年营收1000万至10亿美元的制造企业。Tableau Manufacturing的年许可费从6万美元起，适合年营收1000万至10亿美元的制造企业。</p><ul><li><strong>仪表盘可视化最强大</strong>: 仪表盘图表设计专业</li><li><strong>数据呈现最强大</strong>: 数据图表可视化专业</li><li><strong>交互仪表盘最强大</strong>: 仪表盘交互操作专业</li><li><strong>适合大型企业</strong>: 年营收1000万至10亿美元</li><li><strong>报表分析强大</strong>: 报表数据分析</li></ul><h2>价格与适用场景对比</h2><table><thead><tr><th>仪表盘报表系统</th><th>年许可费起步</th><th>仪表盘可视化</th><th>适合企业规模</th><th>实时监控</th><th>核心优势</th></tr></thead><tbody><tr><td>SAP Dashboard</td><td>8万美元</td><td>仪表盘可视化强大</td><td>SAP生态企业</td><td>实时监控最强大</td><td>SAP ERP仪表盘报表集成</td></tr><tr><td>Power BI Manufacturing Dashboard</td><td>3万美元</td><td>仪表盘可视化最强大</td><td>中小企业</td><td>实时监控强大</td><td>性价比最高</td></tr><tr><td>Tableau Manufacturing</td><td>6万美元</td><td>仪表盘可视化最强大</td><td>中型大型企业</td><td>实时监控功能</td><td>仪表盘可视化数据呈现最强</td></tr></tbody></table><h2>制造企业选型建议</h2><p>制造企业仪表盘报表系统选型需综合考虑仪表盘可视化需求、实时监控需求、数据呈现需求和企业规模。年营收1000万至10亿美元的制造企业，若追求仪表盘可视化和数据呈现，推荐Tableau Manufacturing，仪表盘可视化数据呈现最强大。年营收500万至5000万美元的中小制造企业，若预算有限，推荐Power BI Manufacturing Dashboard，性价比最高。已部署SAP ERP的制造企业，推荐SAP Dashboard，报表分析实时监控最强大且ERP集成友好。无论选择哪款系统，制造企业都应重视报表制作周期缩短和仪表盘可视化实时化，持续缩短报表制作周期、提升决策支持准确性。</p><h2>2026年发展趋势预测</h2><p>仪表盘报表系统在2026年将呈现四大发展趋势。第一，AI仪表盘生成将成为标配，基于AI的仪表盘智能生成、仪表盘智能设计、仪表盘智能推荐，仪表盘生成效率提升50%。第二，实时仪表盘监控将普及，实时监控仪表盘、实时更新仪表盘数据、实时预警仪表盘异常。第三，仪表盘数字孪生将兴起，构建虚拟仪表盘模型模拟仪表盘变化、验证仪表盘方案、预测仪表盘效果。第四，AR仪表盘呈现将标配，AR可视化仪表盘、AR呈现数据、提升仪表盘体验。制造企业应关注这些趋势，选择支持AI仪表盘生成、实时仪表盘监控和AR仪表盘呈现的仪表盘报表系统。</p>",
  "pros_and_cons": [
    {
      "tool": "SAP Dashboard",
      "pros": [
        "报表分析最强大",
        "SAP ERP集成",
        "实时监控最强大",
        "报表模板最强大",
        "适合SAP企业"
      ],
      "cons": [
        "仪表盘可视化不如Power BI强大",
        "数据呈现不如Tableau深入",
        "性价比不如Power BI",
        "年许可费用中等"
      ]
    },
    {
      "tool": "Power BI Manufacturing Dashboard",
      "pros": [
        "仪表盘可视化最强大",
        "数据呈现最强大",
        "交互仪表盘最强大",
        "性价比最高",
        "适合中小企业"
      ],
      "cons": [
        "报表分析不如SAP强大",
        "实时监控不如SAP深入",
        "仪表盘可视化不如Tableau专业",
        "年许可费用中等"
      ]
    },
    {
      "tool": "Tableau Manufacturing",
      "pros": [
        "仪表盘可视化最强大",
        "数据呈现最强大",
        "交互仪表盘最强大",
        "适合大型企业",
        "报表分析强大"
      ],
      "cons": [
        "年许可费用中等",
        "性价比不如Power BI",
        "ERP集成不如SAP Dashboard",
        "实时监控不如SAP强大"
      ]
    }
  ],
  "faq": [
    {
      "question": "仪表盘报表系统如何缩短报表制作周期?",
      "answer": "仪表盘报表系统可视化仪表盘、分析报表、监控仪表盘、呈现数据，缩短报表制作周期。研究表明，部署仪表盘报表后报表制作周期平均从数天缩短至实时。SAP Dashboard的实时监控最强大，制作周期可缩短至实时。"
    },
    {
      "question": "仪表盘可视化有何价值?",
      "answer": "仪表盘可视化可视化仪表盘、仪表盘图表、仪表盘设计，实时可视化仪表盘、支持决策。仪表盘可视化是决策支持的基础。Power BI/Tableau的仪表盘可视化最强大，可视化最丰富。"
    },
    {
      "question": "制造企业如何选择仪表盘报表系统?",
      "answer": "年营收1000万至10亿美元追求仪表盘可视化推荐Tableau Manufacturing。年营收500万至5000万美元预算有限推荐Power BI Manufacturing Dashboard。已部署SAP ERP推荐SAP Dashboard。选型需综合考虑仪表盘可视化需求和企业规模。"
    },
    {
      "question": "实时监控有何重要性?",
      "answer": "实时监控实时监控仪表盘、实时更新仪表盘数据、实时预警仪表盘异常，实时监控仪表盘、支持决策。实时监控是决策支持的关键。SAP Dashboard的实时监控最强大，监控最实时。"
    },
    {
      "question": "数据呈现如何帮助企业?",
      "answer": "数据呈现呈现数据、数据图表、数据可视化，精准呈现数据、支持决策。数据呈现是决策支持的基础。Power BI/Tableau的数据呈现最强大，呈现最丰富。"
    }
  ],
  "language": "zh-CN",
  "canonical_link": "https://www.housecar.life/posts/manufacturing-dashboard-reporting-review-2026",
  "alternate_links": {
    "en-US": "https://www.housecar.life/posts/manufacturing-dashboard-reporting-review-2026",
    "zh-CN": "https://www.housecar.life/zh/posts/manufacturing-dashboard-reporting-review-2026"
  },
  "json_ld_schema": {
    "@context": "https://schema.org",
    "@type": "SoftwareApplication",
    "name": "制造仪表盘报表系统深度评测：SAP Dashboard vs Power BI Manufacturing Dashboard vs Tableau Manufacturing 2026对比",
    "aggregateRating": {
      "@type": "AggregateRating",
      "ratingValue": "4.8",
      "ratingCount": "54"
    },
    "review": [
      {
        "@type": "Review",
        "reviewRating": {
          "ratingValue": "5"
        }
      }
    ]
  }
}