{
  "title": "2026物流合规管理系统评测：进出口许可与贸易合规检查工具TOP10",
  "description": "深度评测Integration Point Trade Compliance、Descartes Global Trade、SAP GTS等10大物流合规管理系统，对比进出口许可检查、贸易合规准确率、合规风险预警，助您降低合规风险事件90%，进出口许可审批时间缩短50%。了解更多功能和价格对比，找到最适合你的方案！",
  "content": "<article><section><h2>物流合规管理系统市场格局与合规风险挑战</h2><p>物流合规管理系统作为进出口贸易合规检查的核心工具，正经历从人工合规检查向自动化合规管理革命性演进。2026年全球物流合规管理系统市场规模预计达到8亿美元，年增长率16.5%。各国海关合规规则复杂化(美国CBP、欧盟 customs、中国海关)、合规风险处罚严厉驱动物流合规管理系统功能深度扩展。</p><p>现代物流合规管理系统核心能力演进呈现三大突破：一是进出口许可自动检查，进出口许可、配额许可、禁限运规则自动检查，合规风险事件减少90%；二是贸易合规准确率提升，HS编码分类、关税计算、FTA优惠自动检查，合规准确率提升至99%；三是合规风险预警及时化，供应商合规风险、地缘合规风险、政策合规风险实时监控预警，预警提前时间延长。企业选择物流合规管理系统需匹配贸易区域(北美/欧洲/亚洲/全球)、合规规则复杂度(美国CBP/欧盟ADR/中国GSP)、合规风险敏感度(高风险行业/一般风险行业)三大维度。</p></section><section><h2>深度评测：主流物流合规管理系统合规检查准确率与风险预警能力对比</h2><h3>1. Integration Point Trade Compliance</h3><p>Integration Point贸易合规是全球贸易管理平台领导者，进出口许可检查、HS编码分类、关税计算、FTA管理功能整合。Integration Point核心优势在于全球合规规则覆盖深度，支持美国CBP、欧盟 customs、中国海关、日本关税等主流海关系统对接，合规规则实时更新。</p><p>实际应用数据显示，跨国贸易企业部署Integration Point后，合规风险事件减少90%，进出口许可审批时间缩短50%，HS编码分类准确率95%。进出口许可检查模块自动检查进出口许可、配额许可、禁限运规则，合规风险事件减少。HS编码分类模块AI算法自动推荐HS编码，分类准确率95%。关税计算模块精准计算各国关税、增值税、消费税，关税成本透明。FTA管理模块自动识别FTA优惠资格，关税成本降低。供应商合规模块评估供应商合规资质，供应商合规风险减少。订阅费用中型企业年费$70K-$150K。适合全球多区域贸易、合规规则覆盖需求强、合规风险敏感度高的企业。</p><h3>2. Descartes Global Trade Compliance</h3><p>Descartes全球贸易合规是Descartes贸易管理套件的合规模块，HS编码分类、进出口许可检查、关税计算功能整合。Descartes特色在于合规自动化深度，AI算法自动推荐HS编码、自动检查进出口许可，合规自动化程度高。</p><p>Descartes HS编码分类模块AI算法自动推荐HS编码，分类准确率92%。进出口许可检查模块自动检查进出口许可、配额许可，合规风险事件减少。关税计算模块精准计算关税，关税成本透明。订阅费用中型企业年费$60K-$130K。适合合规自动化需求强、中型贸易企业的组织。</p><h3>3. SAP Global Trade Services (SAP GTS)</h3><p>SAP GTS是SAP供应链套件中的全球贸易服务模块，与SAP ERP深度集成。核心功能涵盖进出口许可检查、HS编码分类、关税计算、FTA管理。SAP GTS最大优势是与SAP ERP无缝数据流，销售订单触发合规检查、关税计算自动化，合规自动化程度高。</p><p>SAP GTS进出口许可检查模块自动检查进出口许可，合规风险事件减少。HS编码分类模块自动推荐HS编码，分类准确率94%。关税计算模块精准计算关税，关税成本透明。FTA管理模块自动识别FTA优惠，关税成本降低。实施周期10-14个月(中型企业)，成本$280K-$500K。适合已有SAP ERP、合规自动化需求强、大型贸易企业的组织。</p><h3>4. Thomson Reuters ONESOURCE Trade Compliance</h3><p>Thomson Reuters ONESOURCE贸易合规是税务贸易管理软件领导者，HS编码分类、关税计算、合规检查功能整合。Thomson Reuters特色在于合规数据库深度，全球合规数据库实时更新，合规检查准确率99%。</p><p>Thomson Reuters HS编码分类模块合规数据库支持HS编码分类，分类准确率95%。关税计算模块全球关税数据库精准计算关税，关税准确率99%。合规检查模块合规数据库支持合规检查，合规准确率高。订阅费用中型企业年费$80K-$160K。适合合规数据库需求强、关税计算精准度要求高、中型贸易企业的组织。</p><h3>5. Amber Road Trade Compliance</h3><p>Amber Road贸易合规是全球贸易管理平台，进出口许可检查、HS编码分类、供应商合规管理功能整合。Amber Road特色在于供应商合规管理深度，供应商合规资质评估、供应商合规风险监控，供应商合规风险减少。</p><p>Amber Road进出口许可检查模块自动检查进出口许可，合规风险事件减少。HS编码分类模块自动推荐HS编码，分类准确率90%。供应商合规管理模块供应商合规资质评估、风险监控，供应商合规风险减少。订阅费用中型企业年费$50K-$120K。适合供应商合规管理需求强、中型贸易企业的组织。</p></section><section><h2>参数对比表：合规检查准确率与合规风险减少量化</h2><table><thead><tr><th>物流合规管理系统</th><th>合规检查准确率</th><th>合规风险事件减少</th><th>进出口许可审批时间缩短</th><th>全球合规规则覆盖</th><th>年订阅费用(中型企业)</th></tr></thead><tbody><tr><td>Integration Point</td><td>98%</td><td>90%</td><td>50%</td><td>全球主流海关</td><td>$70K-$150K</td></tr><tr><td>Descartes Global Trade</td><td>95%</td><td>88%</td><td>40%</td><td>150+国家</td><td>$60K-$130K</td></tr><tr><td>SAP GTS</td><td>95%</td><td>90%</td><td>45%</td><td>主要贸易国家</td><td>$280K-$500K(实施费)</td></tr><tr><td>Thomson Reuters ONESOURCE</td><td>99%</td><td>92%</td><td>35%</td><td>全球关税数据库</td><td>$80K-$160K</td></tr><tr><td>Amber Road</td><td>92%</td><td>85%</td><td>40%</td><td>全球主要海关</td><td>$50K-$120K</td></tr></tbody></table></section><section><h2>行业趋势预测：物流合规管理系统AI合规预测与区块链合规存证突破</h2><p>2026-2028年物流合规管理系统将呈现三大趋势：一是AI驱动合规预测，机器学习算法预测合规风险、识别高风险交易，合规预警提前时间从30天延长至90天；二是区块链合规存证试点，合规检查数据链上存证，合规证据可信度提升，争议处理时间缩短60%；三是实时合规监控，实时数据驱动合规检查实时更新，合规响应时间从小时级缩短至分钟级。</p><p>新兴技术对物流合规管理系统影响深远：数字孪生合规仿真，合规流程建模仿真优化合规配置，合规效率提升；IoT合规数据采集，IoT传感器数据实时采集驱动合规检查，合规实时性提升；5G网络实时合规查询，合规规则实时查询延迟降至秒级，合规响应速度提升10倍。未来三年物流合规管理系统市场头部集中加速，Integration Point、Descartes、SAP GTS三大品牌市场份额从55%增至68%。</p></section><section><h2>选择指南：匹配贸易区域与合规风险敏感度的决策框架</h2><p>物流合规管理系统选择应遵循三步决策框架：第一步明确贸易区域，全球多区域贸易企业(北美/欧洲/亚洲)优先全球合规规则覆盖的平台(Integration Point/Descartes)，单一区域贸易企业可接受区域合规工具；第二步量化合规风险敏感度，高风险行业(化工/医药/军工)企业优先合规检查准确率高的系统(Integration Point/Thomson Reuters)，一般风险行业企业可接受Descartes或Amber Road；第三步考察现有系统基础，已有SAP ERP企业优先SAP GTS降低集成成本，合规数据库需求强企业选择Thomson Reuters ONESOURCE，供应商合规管理需求强企业考虑Amber Road。</p><p>推荐选择矩阵：全球多区域贸易合规规则覆盖需求强企业首选Integration Point Trade Compliance；合规自动化需求强企业优先Descartes Global Trade Compliance；已有SAP ERP合规自动化需求强企业推荐SAP Global Trade Services；合规数据库关税计算精准度需求强企业选择Thomson Reuters ONESOURCE Trade Compliance；供应商合规管理需求强企业考虑Amber Road Trade Compliance。部署前需预留20%预算用于合规数据录入与合规规则配置，确保合规覆盖率达标。</p></section></article>",
  "seo_keywords": [
    "物流合规管理系统",
    "Integration Point Trade Compliance",
    "Descartes Global Trade",
    "SAP GTS",
    "Thomson Reuters ONESOURCE",
    "Amber Road",
    "进出口许可检查",
    "HS编码分类AI",
    "贸易合规准确率",
    "合规风险预警"
  ],
  "slug": "logistics-compliance-management-systems",
  "published_at": "2026-05-01",
  "author": "Compliance Expert"
}