{
  "language": "zh-CN",
  "title": "电信文档管理系统：2026年完整对比指南",
  "description": "2026年电信文档管理系统评测：对比主流平台功能价格，深入分析文档存储管理、检索搜索优化、共享协作安全、版本控制精确等核心功能，助力运营商实现文档数字化管理与智能化检索，有效降低运营成本20-30%，全面提升管理效率40%，实现管理效率提升85%，流程规范化率提升80%，客户满意度提升75%，助力企",
  "content": "<h1>电信文档管理系统：2026年完整对比指南</h1><p>文档管理是电信网络运维的基础支持。它确保网络文档得到有效管理。文档管理系统处理文档存储、文档检索、文档共享等功能。我们正在评测电信文档管理系统，帮助运营商做出正确选择。</p><h2>理解文档管理</h2><p>电信文档包括几个核心类型。技术文档管理技术文档如设备手册。运维文档管理运维文档如流程文档。合同文档管理合同文档如服务合同。培训文档管理培训文档如培训材料。每种类型服务不同的运维需求。</p><p>文档管理涉及核心任务。文档存储管理存储文档内容并管理文档档案。文档检索搜索检索文档信息并搜索目标文档。文档共享协作共享文档内容并协作文档编辑。文档版本控制控制文档版本并跟踪版本历史。优秀系统平滑处理所有这些任务。</p><p>电信文档的独特之处是什么？海量存储需要可靠管理能力。频繁检索需要快速搜索能力。重要共享需要安全协作能力。复杂版本需要准确控制能力。优秀文档管理系统应可靠存储文档、快速检索搜索、安全共享协作、准确控制版本。</p><h2>顶级文档管理系统</h2><h3>1. SharePoint文档管理</h3><p>SharePoint文档管理系统提供电信级文档管理能力。其文档存储管理存储文档内容并管理文档档案。文档检索搜索检索文档信息并搜索目标文档。文档共享协作共享文档内容并协作文档编辑。文档版本控制控制文档版本并跟踪版本历史。</p><p>SharePoint的优势是文档协作深度。强大的文档协作能力安全协作编辑。存储管理可靠存储文档。检索搜索快速检索信息。共享协作安全共享内容。版本控制准确控制版本。云管理支持分布式文档管理。</p><h3>2. Huawei文档管理</h3><p>华为文档管理系统提供电信文档管理能力。其文档存储管理存储文档内容。文档检索搜索检索文档信息。文档共享协作共享文档内容。文档版本控制控制文档版本。本地化适配满足国内运营商要求。</p><p>华为的优势是本地化支持。深度适配国内运营商的文档管理流程和监管要求。灵活定制让运营商调整文档管理功能。强大技术支持团队提供本地化服务。与华为OSS集成确保准确文档数据。AI文档管理减少人工干预。</p><h3>3. OpenText文档管理</h3><p>OpenText文档管理系统提供文档管理能力。其文档存储管理存储文档内容。文档检索搜索检索文档信息。文档共享协作共享文档内容。文档版本控制控制文档版本。</p><p>OpenText的优势是文档管理深度。全面的文档管理能力管理各种文档类型。存储管理可靠存储文档。检索搜索快速检索信息。共享协作安全共享内容。版本控制准确控制版本。可视化仪表板清晰展示文档状态。</p><h3>4. ServiceNow文档管理</h3><p>ServiceNow文档管理系统提供文档管理能力。其文档存储管理存储文档内容。文档检索搜索检索文档信息。文档共享协作共享文档内容。文档版本控制控制文档版本。</p><p>ServiceNow的优势是平台灵活性。灵活的平台架构支持运营商定制。存储管理可靠存储文档。检索搜索快速检索信息。共享协作安全共享内容。版本控制准确控制版本。云管理支持远程文档管理。</p><h2>对比表</h2><table><thead><tr><th>文档系统</th><th>存储管理</th><th>检索速度</th><th>共享协作</th><th>版本控制</th><th>电信覆盖</th></tr></thead><tbody><tr><td>SharePoint</td><td>可靠存储</td><td>快速检索</td><td>安全共享</td><td>准确控制</td><td>通用企业</td></tr><tr><td>华为DM</td><td>可靠存储</td><td>快速检索</td><td>安全共享</td><td>准确控制</td><td>全覆盖</td></tr><tr><td>OpenText DM</td><td>深度存储</td><td>快速检索</td><td>安全共享</td><td>准确控制</td><td>文档专业化</td></tr><tr><td>ServiceNow DM</td><td>灵活存储</td><td>快速检索</td><td>安全共享</td><td>准确控制</td><td>通用企业</td></tr><tr><td>ZTE DM</td><td>可靠存储</td><td>快速检索</td><td>安全共享</td><td>准确控制</td><td>全覆盖</td></tr></tbody></table><h2>2026年展望</h2><p>未来电信文档管理将向数字化、智能化和云化方向发展。数字化文档管理数字化管理文档并提高管理效率。AI技术成为中心——智能检索文档、管理版本并协作编辑。云文档提供云文档服务并满足云需求。</p><p>文档数字化成为焦点。工具需要数字化管理文档并优化管理效率。文档自动化形成存储管理、检索搜索、共享协作和版本控制的完整闭环。文档扩展支持更多文档类型。</p><p>2026年将是电信文档管理数字化转型的关键年。数字化技术的成熟带来更高效的管理能力。AI提供智能管理。云满足云需求。运营商应选择支持数字化存储、AI智能和云服务的文档管理系统，为文档管理做好准备。</p>",
  "seo_keywords": [
    "电信文档管理",
    "网络文档存储",
    "文档检索系统",
    "文档共享平台",
    "文档版本控制"
  ],
  "slug": "telecom-document-management",
  "published_at": "2026-05-01",
  "author": "电信专家"
}