{
  "title": "人才池管理软件评测：2026年候选人数据库平台深度对比",
  "description": "全面评测2026年人才池管理软件，包括候选人存储、技能分类、长期关系维护等功能对比，帮助招聘机构优化人才储备。",
  "content": "<h2>人才池管理概述</h2><p>人才池管理是招聘机构的核心竞争力。在2026年人才竞争激烈的市场环境下，维护高质量人才储备、建立长期人才关系、实现候选人复用成为机构生存发展的关键。人才池管理软件帮助机构实现候选人集中存储、技能智能分类、长期关系维护、快速匹配检索等功能。</p><p>人才池管理软件的核心价值在于提升候选人复用率50%，减少重复获取成本40%，增强长期人才转化率35%。根据行业调研数据，采用专业人才池管理软件的招聘机构平均候选人数据库利用率提升45%，人才储备周转率提升30%，招聘响应速度提升50%。</p><h2>主流人才池管理平台评测</h2><h3>Bullhorn Talent Pool</h3><p>Bullhorn人才池管理模块作为行业标杆，功能覆盖候选人存储、分类、检索、匹配等全流程。候选人数据库支持无限量存储，自动解析简历生成标准化档案。技能分类功能支持自定义标签体系，自动技能提取和关联。</p><p>搜索功能支持多维度检索——技能、经验、地域、薪资、行业等。高级筛选功能可组合多个条件，精准定位人才。匹配推荐引擎基于AI算法，根据岗位需求自动推荐合适候选人。</p><p>长期关系维护功能支持候选人培育计划、自动化跟进、忠诚度评分。候选人活跃度分析识别高价值人才，帮助顾问优先维护。数据分析仪表盘展示人才池规模、利用率、转化率等关键指标。价格方面，人才池模块作为核心CRM组成部分，整体每用户每月约80-120美元。</p><h3>Loxo Talent Database</h3><p>Loxo人才池管理强调AI驱动和智能化。候选人数据库支持智能简历解析，自动提取关键信息生成档案。技能分类功能支持AI自动技能提取和标签关联，减少人工分类工作量。</p><p>搜索功能支持自然语言检索，AI理解查询意图返回相关结果。匹配推荐引擎基于机器学习，持续优化推荐准确度。相似候选人推荐功能帮助顾问发现相似人才，扩展候选人选择。</p><p>长期关系维护功能支持自动化培育序列、触达时机优化、响应预测。候选人价值评分系统评估人才潜力，帮助顾问识别高价值人选。数据分析模块展示人才池健康度、转化率、培育效果。定价采用订阅制，专业版每用户每月75美元，企业版每用户每月120美元。</p><h3>Recruiterflow Talent Pool</h3><p>Recruiterflow人才池管理模块强调自动化和易用性。候选人数据库支持多格式简历解析，自动生成标准化档案。技能分类功能支持标签体系，可自定义分类规则。</p><p>搜索功能支持多维度检索，组合筛选条件精准定位人才。匹配推荐引擎根据岗位需求自动推送候选人。长期关系维护功能支持自动化培育计划、邮件序列、跟进提醒。</p><p>候选人活跃度分析识别需要优先维护的人才。数据分析模块展示人才池规模、利用率、转化率等指标。定价方面，专业版每用户每月75美元，企业版每用户每月120美元。客户反馈认为自动化功能突出，但深度分析能力相对有限。</p><h3>HireHunt Talent Pool</h3><p>HireHunt专注候选人长期培育，人才池管理围绕关系维护设计。候选人数据库支持简历解析和信息存储。技能分类功能支持标签体系和手动分类。</p><p>搜索功能支持多维度检索，筛选合适候选人。长期培育功能表现突出，支持设置培育计划、自动化跟进序列、触达时机提醒。候选人生命周期管理帮助顾问维护从初次接触到入职跟踪的全过程。</p><p>候选人忠诚度评分系统评估关系深度，帮助识别高价值人才。数据分析模块展示培育效果、转化率、响应统计。定价相对亲民，标准版每用户每月50美元，专业版每用户每月80美元。客户评价认为培育功能完善，但搜索匹配能力相对基础。</p><h3>DATIS Talent Pool</h3><p>DATIS定位候选人数据管理，人才池管理围绕数据质量设计。候选人数据库支持多源信息整合——简历、社交媒体、面试记录、测评结果等。数据清洗功能自动识别重复、错误、过期信息，维护数据质量。</p><p>技能分类功能支持标准化标签体系，确保分类一致性。搜索功能支持多维度检索，精准定位人才。合规管理模块符合GDPR等数据保护法规，支持隐私请求处理和数据删除跟踪。</p><p>数据分析模块提供数据质量报告、人才池健康度评估、利用率统计。定价采用订阅制，标准版每用户每月60美元，专业版每用户每月90美元。客户反馈认为数据管理功能完善，但培育工具相对基础。</p><h2>人才池管理平台对比表</h2><table><thead><tr><th>平台名称</th><th>市场定位</th><th>价格区间</th><th>候选人存储</th><th>技能分类</th><th>长期培育</th></tr></thead><tbody><tr><td>Bullhorn</td><td>行业标杆</td><td>80-120美元/用户/月</td><td>优秀</td><td>优秀</td><td>良好</td></tr><tr><td>Loxo</td><td>AI驱动</td><td>75-120美元/用户/月</td><td>优秀</td><td>优秀</td><td>良好</td></tr><tr><td>Recruiterflow</td><td>自动化</td><td>75-120美元/用户/月</td><td>良好</td><td>良好</td><td>优秀</td></tr><tr><td>HireHunt</td><td>培育专注</td><td>50-80美元/用户/月</td><td>良好</td><td>基础</td><td>优秀</td></tr><tr><td>DATIS</td><td>数据管理</td><td>60-90美元/用户/月</td><td>优秀</td><td>良好</td><td>基础</td></tr></tbody></table><h2>2026年人才池管理趋势</h2><p>人才池管理市场呈现以下发展趋势：</p><p>AI智能分类成为标配。AI算法自动提取技能、生成标签、关联分类，大幅减少人工处理工作量。预计2027年，AI分类准确率将突破90%，人才池维护效率提升50%。</p><p>长期培育功能深化发展。人才池管理将越来越重视长期关系维护——自动化培育序列、触达时机优化、忠诚度预测、生命周期管理。候选人培育将成为人才池的核心功能。</p><p>数据质量管理增强。候选人数据库需要持续维护数据质量——清洗重复、更新过期、补充缺失。数据质量管理功能将成为人才池管理的重要模块。</p><p>合规管理要求加强。候选人数据存储和使用需要符合各地区数据保护法规。人才池管理软件将内置更多合规检测功能，自动识别风险操作、管理隐私请求。</p><p>预测分析持续增强。候选人转化预测、离职风险评估、价值预测等前瞻性洞察将帮助机构优化人才池策略。预测分析将成为人才池管理的核心能力。</p><h2>选择建议</h2><p>招聘机构选择人才池管理软件应关注以下维度：候选人数据库容量和扩展性支持人才储备规模；技能分类自动化程度减少人工工作量；搜索和匹配功能效率影响人才检索；长期培育功能深度支持关系维护；数据分析能力提供人才池健康洞察；合规管理功能符合各地区法规要求；集成能力连接外部数据源；成本结构匹配机构预算约束。建议安排多平台试用，验证分类和匹配效果，选择最适合人才管理需求的方案。</p>",
  "seo_keywords": [
    "人才池管理",
    "候选人数据库",
    "人才储备",
    "技能分类",
    "候选人培育",
    "Loxo",
    "Bullhorn",
    "人才管理软件"
  ],
  "slug": "talent-pool-management-software-2026",
  "published_at": "2026-05-01",
  "author": "人才储备研究院"
}