{
  "title": "精选推荐: 体育用品滞销商品处理策略: 智能清仓优化库存结构 | 2026 Review",
  "description": "Deep解析Sporting Goods滞销商品处理Strategy，涵盖滞销识别、清仓Pricing、渠道选择等Core功能，Help力体育零售商Reduce滞销损失OptimizeInventory结构。. Discover features and pricing to find your ideal.",
  "content": "<h1>体育用品滞销商品处理策略：智能清仓优化库存结构</h1><h2>背景与滞销痛点</h2><p>体育用品滞销商品类型多样：过季商品（季节性商品错过销售高峰）、过款商品（新款上市导致旧款滞销）、过号商品（尺码断码导致滞销）、过价商品（价格偏高导致滞销）。滞销商品占用库存资金、占用仓储空间、影响库存周转，滞销处理是体育零售库存管理的关键挑战。传统滞销处理依赖人工判断和简单折扣，滞销识别滞后、清仓定价不准、清仓渠道单一，滞销损失高达库存成本的20%。智能滞销处理通过滞销识别、清仓定价、渠道优化，滞销识别提前期延长至30天，滞销损失降低50%，库存结构优化效率提升40%。本文深度解析五大滞销处理解决方案。</p><h2>核心滞销处理评测</h2><h3>1. ClearancePOS Sports</h3><p>ClearancePOS Sports是滞销处理的标杆产品，核心功能覆盖清仓全流程。滞销识别引擎自动识别滞销商品（滞销定义：30天无销售），识别准确率92%。滞销预警模块滞销预警提前30天，预警准确率88%。清仓定价引擎智能计算清仓定价（动态折扣、阶梯折扣），定价准确率90%。清仓渠道系统智能选择清仓渠道（门店清仓、线上清仓、批发清仓），渠道选择准确率85%。清仓执行模块自动化执行清仓活动，执行效率提升60%。清仓追踪系统追踪清仓执行状态，追踪完整度98%。清仓分析引擎分析清仓效果和规律，分析深度提升60%。定价为月付订阅模式，清仓基础版$499/月，清仓专业版$999/月，适合中型体育用品连锁。</p><h3>2. DiscountPOS Athletic</h3><p>DiscountPOS Athletic专注于清仓定价，打造智能折扣体系。折扣计算引擎智能计算清仓折扣（成本定价、需求定价、竞品定价），计算准确率95%。折扣优化模块优化折扣策略（折扣幅度、折扣时机），折扣优化效率提升40%。折扣测试系统测试折扣效果（A/B测试），测试准确率90%。折扣调整引擎动态调整折扣幅度，调整响应速度低于24小时。折扣追踪模块追踪折扣执行状态，追踪完整度98%。折扣分析仪表板分析折扣效果和规律，分析深度提升60%。定价为年付授权模式，折扣基础版$4,999/年，折扣增强版$8,999/年，适合折扣策略复杂的体育零售商。</p><h3>3. ChannelPOS Sports</h3><p>ChannelPOS Sports专注于清仓渠道，打造多渠道清仓体系。渠道整合模块整合多清仓渠道（门店清仓、线上清仓、批发清仓、捐赠渠道），渠道覆盖率100%。渠道选择引擎智能选择最佳清仓渠道，选择准确率88%。渠道协同系统协同多渠道清仓执行，协同效率提升40%。渠道成本优化模块优化渠道清仓成本，成本降低30%。渠道追踪模块追踪渠道清仓状态，追踪完整度95%。渠道优化引擎优化渠道资源配置，资源优化效率提升35%。定价为季度订阅模式，渠道基础版$699/季，渠道增强版$1,199/季，适合多渠道清仓的体育零售商。</p><h3>4. TimedPOS Athletic</h3><p>TimedPOS Athletic专注于清仓时机，打造时机优化体系。时机预测引擎预测最佳清仓时机，预测准确率85%。时机优化模块优化清仓时机（避免旺季、避开高峰），时机优化效率提升40%。时机预警系统预警清仓时机，预警提前期7天。时机调整引擎动态调整清仓时机，调整响应速度低于24小时。时机追踪模块追踪时机执行状态，追踪完整度98%。时机分析仪表板分析时机效果和规律，分析深度提升60%。定价为月付订阅模式，时机基础版$449/月，时机增强版$799/月，适合时机敏感的体育零售商。</p><h3>5. StructurePOS Sports</h3><p>StructurePOS Sports专注于库存结构优化，打造结构化清仓体系。结构分析引擎分析库存结构（品类结构、尺码结构、价格结构），分析准确率95%。结构优化模块优化库存结构（调整配比、清理冗余），结构优化效率提升40%。结构预警系统预警结构异常（结构失衡、结构冗余），预警提前期10天。结构调整引擎动态调整库存结构，调整响应速度低于24小时。结构追踪模块追踪结构调整状态，追踪完整度98%。结构可视化仪表板可视化展示库存结构，可视化直观度提升70%。定价为弹性订阅模式，按库存规模收费，小规模$399/月，中规模$699/月，大规模$999/月，适合库存结构复杂的体育零售商。</p><h2>滞销处理对比表</h2><table><thead><tr><th>系统名称</th><th>核心功能</th><th>识别准确率</th><th>滞销损失降低</th><th>结构优化效率</th><th>定价模式</th><th>适用场景</th></tr></thead><tbody><tr><td>ClearancePOS Sports</td><td>清仓全流程</td><td>92%</td><td>-50%</td><td>+40%</td><td>月付$499-999</td><td>中型连锁</td></tr><tr><td>DiscountPOS Athletic</td><td>清仓定价</td><td>95%</td><td>-40%</td><td>+30%</td><td>年付$4,999-8,999</td><td>折扣策略复杂</td></tr><tr><td>ChannelPOS Sports</td><td>清仓渠道</td><td>选择88%</td><td>-30%</td><td>+35%</td><td>季度$699-1,199</td><td>多渠道清仓</td></tr><tr><td>TimedPOS Athletic</td><td>清仓时机</td><td>85%</td><td>-35%</td><td>+40%</td><td>月付$449-799</td><td>时机敏感</td></tr><tr><td>StructurePOS Sports</td><td>结构优化</td><td>95%</td><td>-45%</td><td>+40%</td><td>弹性$399-999</td><td>库存结构复杂</td></tr></tbody></table><h2>滞销处理策略建议</h2><p>滞销处理策略需匹配零售商特征：追求清仓全流程的零售商优先部署ClearancePOS Sports，全流程管理快速见效；折扣策略复杂的零售商引入DiscountPOS Athletic，智能定价优化折扣；多渠道清仓的零售商选择ChannelPOS Sports，多渠道协同最大化覆盖；时机敏感的零售商部署TimedPOS Athletic，时机优化避免损失；库存结构复杂的零售商采用StructurePOS Sports，结构优化调整配比。建议滞销处理与POS收银联动，销售数据实时反馈滞销识别模型，销售与滞销管理一体化。</p><h2>2026年滞销趋势预测</h2><p>体育用品滞销处理呈现三大演进方向：一是滞销识别提前，滞销识别提前期从30天延长至60天，滞销准备更加充分；二是清仓定价智能化深化，AI自动生成清仓定价和折扣策略，智能化占比突破70%；三是清仓渠道生态化兴起，清仓渠道延伸到二手平台、捐赠渠道、回收渠道，清仓渠道多元化。预计2026年滞销处理普及率超过80%，滞销损失降低成为零售核心竞争力。</p>",
  "seo_keywords": [
    "滞销商品处理",
    "Sporting Goods清仓Strategy",
    "Smart清仓Pricing",
    "体育零售Inventory清理",
    "滞销识别System"
  ],
  "slug": "sports-inventory-clearance-strategy",
  "published_at": "2026-05-01",
  "author": "体育滞销处理研究院",
  "language": "zh-CN",
  "canonical_link": "https://www.housecar.life/posts/sports-inventory-clearance-strategy",
  "alternate_links": {
    "en-US": "https://www.housecar.life/posts/sports-inventory-clearance-strategy",
    "zh-CN": "https://www.housecar.life/zh/posts/sports-inventory-clearance-strategy"
  },
  "category": "sporting-goods-retail-tools"
}