{
  "title": "精选推荐: 体育用品季节性库存管理: 应对销售高峰与低谷 | 2026 Review",
  "description": "Deep解析Sporting Goods季节性InventoryManagementStrategy，涵盖季节Forecast、备货计划、清仓Optimize等Core功能，Help力体育零售商应对季节性销售波动。. Discover features and pricing to find your ide",
  "content": "<h1>体育用品季节性库存管理：应对销售高峰与低谷</h1><h2>背景与季节性挑战</h2><p>体育用品销售呈现显著季节性特征：夏季游泳用品（泳衣、游泳镜、浮板）销售高峰、冬季滑雪装备（滑雪板、滑雪服、护具）需求激增、春季跑步装备（跑步鞋、运动服）热销、秋季球类装备（篮球、足球、羽毛球）需求旺盛。季节性波动导致库存管理难度倍增：高峰期备货不足导致缺货损失、低谷期库存积压导致资金占用。季节性库存管理通过季节预测、智能备货、动态清仓，季节性缺货率降低60%，季节性积压损失降低50%，季节性库存周转率提升45%。本文深度解析五大季节性库存管理解决方案。</p><h2>核心季节性管理评测</h2><h3>1. SeasonalPOS Sports</h3><p>SeasonalPOS Sports是季节性库存管理的标杆产品，核心功能覆盖季节全周期。季节销售预测引擎通过历史数据、天气变化、赛事日程预测季节销售高峰和低谷，预测准确率92%。季节备货计划系统提前30天生成季节备货计划，备货匹配度提升50%。季节库存预警模块预警季节库存风险（高峰缺货、低谷积压），预警提前期15天。季节清仓引擎自动化清仓季节尾货，清仓效率提升60%。季节转换系统自动化季节转换库存调整，转换响应时间低于7天。季节分析仪表板分析季节销售规律，分析深度提升70%。定价为月付订阅模式，季节基础版$499/月，季节专业版$999/月，适合季节性波动明显的体育零售商。</p><h3>2. PeakPOS Athletic</h3><p>PeakPOS Athletic专注于销售高峰管理，打造高峰期备货保障体系。高峰预测引擎预测销售高峰时段和高峰商品，预测准确率88%。高峰备货系统高峰期前备货保障，备货充足率95%。高峰库存监控模块高峰期实时监控库存，监控响应速度低于1小时。高峰调拨引擎高峰期跨店调拨保障供应，调拨成功率90%。高峰预警系统高峰缺货预警，预警提前期3天。高峰分析模块高峰销售复盘，分析深度提升60%。定价为年付授权模式，高峰基础版$5,999/年，高峰增强版$9,999/年，适合高峰期销售占比高的体育零售商。</p><h3>3. ValleyPOS Sports</h3><p>ValleyPOS Sports专注于销售低谷管理，打造低谷期库存优化体系。低谷预测引擎预测销售低谷时段和低谷商品，预测准确率90%。低谷库存优化模块低谷期库存削减优化，库存占用降低40%。低谷清仓系统低谷期清仓促销，清仓效率提升50%。低谷库存预警预警低谷库存积压，预警提前期10天。低谷成本控制引擎低谷期库存成本控制，成本降低35%。低谷分析模块低谷销售分析，分析深度提升60%。定价为季度订阅模式，低谷基础版$699/季，低谷增强版$1,199/季，适合低谷期库存压力大的体育零售商。</p><h3>4. TransitionPOS Athletic</h3><p>TransitionPOS Athletic专注于季节转换管理，打造平滑转换体系。转换预测引擎预测季节转换时机，预测准确率85%。转换计划系统生成季节转换库存调整计划，计划完整度95%。转换执行模块自动化执行季节转换调整，执行效率提升70%。转换预警引擎季节转换库存预警，预警提前期14天。转换成本控制系统转换成本控制，成本降低30%。转换分析模块转换效果分析，分析深度提升60%。定价为月付订阅模式，转换基础版$449/月，转换增强版$749/月，适合季节转换频繁的体育零售商。</p><h3>5. CyclePOS Sports</h3><p>CyclePOS Sports专注于库存周期管理，打造周期性库存优化体系。周期分析引擎分析库存周期规律，分析准确率90%。周期预测模块预测库存周期高峰和低谷，预测准确率88%。周期备货系统周期备货计划，备货匹配度提升45%。周期清仓引擎周期清仓优化，清仓效率提升40%。周期成本控制模块周期成本控制，成本降低30%。周期可视化仪表板可视化展示库存周期，可视化直观度提升70%。定价为弹性订阅模式，按库存周期复杂度收费，简单$299/月，复杂$599/月，超复杂$999/月，适合库存周期规律明显的体育零售商。</p><h2>季节性管理对比表</h2><table><thead><tr><th>系统名称</th><th>核心功能</th><th>预测准确率</th><th>缺货率降低</th><th>积压损失降低</th><th>定价模式</th><th>适用场景</th></tr></thead><tbody><tr><td>SeasonalPOS Sports</td><td>季节全周期</td><td>92%</td><td>-60%</td><td>-50%</td><td>月付$499-999</td><td>季节性波动明显</td></tr><tr><td>PeakPOS Athletic</td><td>高峰管理</td><td>88%</td><td>-50%</td><td>-20%</td><td>年付$5,999-9,999</td><td>高峰期占比高</td></tr><tr><td>ValleyPOS Sports</td><td>低谷管理</td><td>90%</td><td>-20%</td><td>-50%</td><td>季度$699-1,199</td><td>低谷期压力大</td></tr><tr><td>TransitionPOS Athletic</td><td>转换管理</td><td>85%</td><td>-40%</td><td>-35%</td><td>月付$449-749</td><td>转换频繁</td></tr><tr><td>CyclePOS Sports</td><td>周期管理</td><td>88%</td><td>-45%</td><td>-40%</td><td>弹性$299-999</td><td>周期规律明显</td></tr></tbody></table><h2>季节性策略建议</h2><p>季节性库存管理策略需匹配季节特征：季节性波动明显的零售商优先部署SeasonalPOS Sports，全周期管理应对波动；高峰期销售占比高的零售商引入PeakPOS Athletic，高峰备货保障供应；低谷期库存压力大的零售商选择ValleyPOS Sports，低谷清仓释放资金；季节转换频繁的零售商部署TransitionPOS Athletic，平滑转换减少损失；库存周期规律明显的零售商采用CyclePOS Sports，周期优化提升效率。建议季节性管理与POS收银联动，销售数据实时反馈季节预测模型，销售与季节管理一体化。</p><h2>2026年季节性趋势预测</h2><p>体育用品季节性库存管理呈现三大演进方向：一是预测提前期延长，季节预测提前期从30天延长至60天，备货准备更加充分；二是动态季节管理普及，季节转换响应时间从7天缩短至3天，实时调整成为常态；三是跨季节库存协同兴起，不同季节库存协同共享，季节性库存僵化率降低70%。预计2026年季节性管理普及率超过70%，季节性库存成本降低成为零售核心竞争力。</p>",
  "seo_keywords": [
    "季节性InventoryManagement",
    "Sporting Goods销售高峰",
    "季节性备货计划",
    "体育零售季节Forecast",
    "季节性清仓Strategy"
  ],
  "slug": "sports-inventory-seasonal-management",
  "published_at": "2026-05-01",
  "author": "体育季节库存研究院",
  "language": "zh-CN",
  "canonical_link": "https://www.housecar.life/posts/sports-inventory-seasonal-management",
  "alternate_links": {
    "en-US": "https://www.housecar.life/posts/sports-inventory-seasonal-management",
    "zh-CN": "https://www.housecar.life/zh/posts/sports-inventory-seasonal-management"
  },
  "category": "sporting-goods-retail-tools"
}